local_ssl_manager/__init__.py
local_ssl_manager/__main__.py
local_ssl_manager/cli.py
local_ssl_manager/logging.py
local_ssl_manager/manager.py
local_ssl_manager/ui/__init__.py
local_ssl_manager/ui/domain_selector.py
local_ssl_manager/utils/__init__.py
local_ssl_manager/utils/certificate.py
local_ssl_manager/utils/system.py
local_ssl_manager/utils/validators.py
local_ssl_manager-0.1.14.dist-info/licenses/LICENSE
local_ssl_manager-0.1.14.dist-info/METADATA
local_ssl_manager-0.1.14.dist-info/WHEEL
local_ssl_manager-0.1.14.dist-info/entry_points.txt
local_ssl_manager-0.1.14.dist-info/top_level.txt
local_ssl_manager-0.1.14.dist-info/RECORD
