Metadata-Version: 2.4
Name: local-ssl-manager
Version: 0.1.14
Summary: Manage local SSL certificates for development environments
Author: Maximilian Bertram
Author-email: Maximilian Bertram <contact@maxbertram.com>
License: MIT
Project-URL: Homepage, https://github.com/MaxBer04/local_ssl_manager
Project-URL: Bug Tracker, https://github.com/MaxBer04/local_ssl_manager/issues
Project-URL: Documentation, https://github.com/MaxBer04/local_ssl_manager#readme
Platform: any
Classifier: Development Status :: 4 - Beta
Classifier: Intended Audience :: Developers
Classifier: License :: OSI Approved :: MIT License
Classifier: Programming Language :: Python :: 3
Classifier: Programming Language :: Python :: 3.8
Classifier: Programming Language :: Python :: 3.9
Classifier: Programming Language :: Python :: 3.10
Classifier: Programming Language :: Python :: 3.11
Classifier: Topic :: Software Development :: Build Tools
Classifier: Topic :: System :: Systems Administration
Classifier: Topic :: Security :: Cryptography
Requires-Python: >=3.8
License-File: LICENSE
Requires-Dist: click>=8.0.0
Requires-Dist: colorama>=0.4.4
Requires-Dist: rich>=10.0.0
Requires-Dist: certifi>=2022.12.7
Provides-Extra: dev
Requires-Dist: pytest>=7.0.0; extra == "dev"
Requires-Dist: pytest-cov>=3.0.0; extra == "dev"
Requires-Dist: black>=22.3.0; extra == "dev"
Requires-Dist: isort>=5.10.1; extra == "dev"
Requires-Dist: flake8>=4.0.1; extra == "dev"
Requires-Dist: mypy>=0.942; extra == "dev"
Requires-Dist: pre-commit>=2.20.0; extra == "dev"
Requires-Dist: pre-commit>=2.20.0; extra == "dev"
Provides-Extra: docs
Requires-Dist: mkdocs>=1.3.0; extra == "docs"
Requires-Dist: mkdocstrings>=0.18.1; extra == "docs"
Requires-Dist: mkdocs-material>=8.2.8; extra == "docs"
Dynamic: license-file
